pyinsole/__init__.py
pyinsole/compat.py
pyinsole/dispatchers.py
pyinsole/exceptions.py
pyinsole/ext/__init__.py
pyinsole/ext/aws/__init__.py
pyinsole/ext/aws/base.py
pyinsole/ext/aws/providers.py
pyinsole/ext/aws/routes.py
pyinsole/ext/aws/translators.py
pyinsole/ext/handlers/__init__.py
pyinsole/ext/handlers/handlers.py
pyinsole/ext/sentry/__init__.py
pyinsole/ext/sentry/sentry.py
pyinsole/handlers.py
pyinsole/managers.py
pyinsole/providers.py
pyinsole/routes.py
pyinsole/runners.py
pyinsole/translators.py
pyinsole/utils.py
pyinsole-0.1.0.dist-info/LICENSE
pyinsole-0.1.0.dist-info/METADATA
pyinsole-0.1.0.dist-info/WHEEL
pyinsole-0.1.0.dist-info/RECORD
