Metadata-Version: 2.1
Name: pyinsole
Version: 0.1.0
Summary: Asynchronous message dispatcher for concurrent tasks processing
License: MIT
Keywords: asyncio,message,dispatcher,tasks,microservices
Author: Eduardo Neto
Author-email: edopneto@gmail.com
Requires-Python: >=3.11
Classifier: Development Status :: 4 - Beta
Classifier: Environment :: Console
Classifier: Intended Audience :: Developers
Classifier: License :: OSI Approved :: MIT License
Classifier: Natural Language :: English
Classifier: Operating System :: OS Independent
Classifier: Programming Language :: Python :: 3
Classifier: Programming Language :: Python :: 3.11
Classifier: Programming Language :: Python :: 3.12
Classifier: Programming Language :: Python :: 3.13
Classifier: Programming Language :: Python :: 3 :: Only
Classifier: Topic :: System :: Distributed Computing
Requires-Dist: aiobotocore (>=2.15.2,<3.0.0)
Requires-Dist: sentry-sdk (>=2.17.0,<3.0.0)
